{
  "name": "pre-production",
  "displayName": "Pre-Production",
  "description": "Pre-production environment configuration for release branches",
  "azure": {
    "resourceGroup": "rg-myapp-preprod",
    "location": "East US",
    "staticWebApp": {
      "name": "swa-myapp-preprod",
      "sku": "Standard"
    },
    "keyVault": {
      "name": "kv-myapp-preprod",
      "sku": "premium"
    }
  },
  "application": {
    "features": {
      "debugMode": false,
      "analytics": true,
      "monitoring": "full"
    },
    "security": {
      "requireAuth": true,
      "cors": {
        "enabled": true,
        "origins": ["https://preprod.myapp.com"]
      }
    },
    "performance": {
      "caching": true,
      "compression": true
    }
  },
  "build": {
    "optimization": true,
    "sourceMaps": true,
    "minification": true
  },
  "monitoring": {
    "logging": {
      "level": "info",
      "console": false
    },
    "metrics": {
      "enabled": true
    }
  },
  "deployment": {
    "autoScaling": true,
    "healthCheck": {
      "enabled": true,
      "timeout": 90
    }
  }
}